[
  {
    "tipo": "3",
    "data": "2019-3-1",
    "valor": 142.0,
    "cpf": "09620676017",
    "cartao": "4753****3153",
    "hora": "15:34:53",
    "dono": "JOÃO MACEDO",
    "loja": "BAR DO JOÃO"
  },
  {
    "tipo": "5",
    "data": "2019-3-1",
    "valor": 132.0,
    "cpf": "55641815063",
    "cartao": "3123****7687",
    "hora": "14:56:7",
    "dono": "MARIA JOSEFINA",
    "loja": "LOJA DO Ó - MATRIZ"
  },
  {
    "tipo": "3",
    "data": "2019-3-1",
    "valor": 122.0,
    "cpf": "84515254073",
    "cartao": "6777****1313",
    "hora": "17:27:12",
    "dono": "MARCOS PEREIRA",
    "loja": "MERCADO DA AVENIDA"
  },
  {
    "tipo": "2",
    "data": "2019-3-1",
    "valor": 112.0,
    "cpf": "09620676017",
    "cartao": "3648****0099",
    "hora": "23:42:34",
    "dono": "JOÃO MACEDO",
    "loja": "BAR DO JOÃO"
  },
  {
    "tipo": "1",
    "data": "2019-3-1",
    "valor": 152.0,
    "cpf": "09620676017",
    "cartao": "1234****7890",
    "hora": "23:30:0",
    "dono": "JOÃO MACEDO",
    "loja": "BAR DO JOÃO"
  },
  {
    "tipo": "2",
    "data": "2019-3-1",
    "valor": 107.0,
    "cpf": "84515254073",
    "cartao": "8723****9987",
    "hora": "12:33:33",
    "dono": "MARCOS PEREIRA",
    "loja": "MERCADO DA AVENIDA"
  },
  {
    "tipo": "2",
    "data": "2019-3-1",
    "valor": 502.0,
    "cpf": "84515254073",
    "cartao": "8473****1231",
    "hora": "23:12:33",
    "dono": "MARCOS PEREIRA",
    "loja": "MERCADO DA AVENIDA"
  },
  {
    "tipo": "3",
    "data": "2019-3-1",
    "valor": 602.0,
    "cpf": "23270298056",
    "cartao": "6777****1313",
    "hora": "17:27:12",
    "dono": "JOSÉ COSTA",
    "loja": "MERCEARIA 3 IRMÃOS"
  },
  {
    "tipo": "1",
    "data": "2019-3-1",
    "valor": 200.0,
    "cpf": "55641815063",
    "cartao": "1234****3324",
    "hora": "9:0:2",
    "dono": "MARIA JOSEFINA",
    "loja": "LOJA DO Ó - MATRIZ"
  },
  {
    "tipo": "5",
    "data": "2019-3-1",
    "valor": 802.0,
    "cpf": "84515254073",
    "cartao": "3123****7687",
    "hora": "14:56:7",
    "dono": "MARCOS PEREIRA",
    "loja": "MERCADO DA AVENIDA"
  },
  {
    "tipo": "2",
    "data": "2019-3-1",
    "valor": 102.0,
    "cpf": "23270298056",
    "cartao": "8473****1231",
    "hora": "23:12:33",
    "dono": "JOSÉ COSTA",
    "loja": "MERCEARIA 3 IRMÃOS"
  },
  {
    "tipo": "3",
    "data": "2019-3-1",
    "valor": 6102.0,
    "cpf": "23270298056",
    "cartao": "6777****1313",
    "hora": "17:27:12",
    "dono": "JOSÉ COSTA",
    "loja": "MERCEARIA 3 IRMÃOS"
  },
  {
    "tipo": "4",
    "data": "2019-3-1",
    "valor": 152.32,
    "cpf": "55641815063",
    "cartao": "1234****6678",
    "hora": "10:0:0",
    "dono": "MARIA JOSEFINA",
    "loja": "LOJA DO Ó - FILIAL"
  },
  {
    "tipo": "8",
    "data": "2019-3-1",
    "valor": 102.03,
    "cpf": "84515254073",
    "cartao": "2344****1222",
    "hora": "12:32:22",
    "dono": "MARCOS PEREIRA",
    "loja": "MERCADO DA AVENIDA"
  },
  {
    "tipo": "3",
    "data": "2019-3-1",
    "valor": 103.0,
    "cpf": "23270298056",
    "cartao": "6777****1313",
    "hora": "17:27:12",
    "dono": "JOSÉ COSTA",
    "loja": "MERCEARIA 3 IRMÃOS"
  },
  {
    "tipo": "9",
    "data": "2019-3-1",
    "valor": 102.0,
    "cpf": "55641815063",
    "cartao": "6228****9090",
    "hora": "0:0:0",
    "dono": "MARIA JOSEFINA",
    "loja": "LOJA DO Ó - MATRIZ"
  },
  {
    "tipo": "4",
    "data": "2019-6-1",
    "valor": 506.17,
    "cpf": "84515254073",
    "cartao": "1234****2231",
    "hora": "10:0:0",
    "dono": "MARCOS PEREIRA",
    "loja": "MERCADO DA AVENIDA"
  },
  {
    "tipo": "2",
    "data": "2019-3-1",
    "valor": 109.0,
    "cpf": "23270298056",
    "cartao": "8723****9987",
    "hora": "12:33:33",
    "dono": "JOSÉ COSTA",
    "loja": "MERCEARIA 3 IRMÃOS"
  },
  {
    "tipo": "8",
    "data": "2019-3-1",
    "valor": 2.0,
    "cpf": "84515254073",
    "cartao": "2344****1222",
    "hora": "12:32:22",
    "dono": "MARCOS PEREIRA",
    "loja": "MERCADO DA AVENIDA"
  },
  {
    "tipo": "2",
    "data": "2019-3-1",
    "valor": 5.0,
    "cpf": "23270298056",
    "cartao": "7677****8778",
    "hora": "14:18:8",
    "dono": "JOSÉ COSTA",
    "loja": "MERCEARIA 3 IRMÃOS"
  },
  {
    "tipo": "3",
    "data": "2019-3-1",
    "valor": 192.0,
    "cpf": "84515254073",
    "cartao": "6777****1313",
    "hora": "17:27:12",
    "dono": "MARCOS PEREIRA",
    "loja": "MERCADO DA AVENIDA"
  }
]